{
  "$schema": "https://raw.githubusercontent.com/electron-userland/electron-builder/master/packages/app-builder-lib/scheme.json",
  "appId": "com.joaobraga.ixipc",
  "productName": "IxiPC",
  "asar": true,
  "directories": {
    "output": "release/${version}",
    "buildResources": "build"
  },
  "files": [
    "dist",
    "dist-electron"
  ],
  "extraResources": [
    {
      "from": "public/logo.ico",
      "to": "logo.ico"
    }
  ],
  "win": {
    "target": [
      {
        "target": "nsis",
        "arch": [
          "x64"
        ]
      }
    ],
    "icon": "public/logo.ico",
    "artifactName": "${productName}-Windows-${version}-${arch}-Setup.${ext}"
  },
  "nsis": {
    "oneClick": false,
    "allowToChangeInstallationDirectory": true,
    "deleteAppDataOnUninstall": false,
    "installerIcon": "public/logo.ico",
    "uninstallerIcon": "public/logo.ico"
  },
  "linux": {
    "target": [
      "AppImage"
    ],
    "icon": "public/logo.png",
    "category": "Utility",
    "artifactName": "${productName}-Linux-${version}-${arch}.${ext}"
  }
}
